{"field":"entertainment","version":"20260714T100606Z","created_at":"2026-07-14T10:06:06.366743+00:00","count":200137,"dim":72,"dtype":"float32-little-endian","use_freq":true,"candidate_schema":"{title}. Format: {type}. [Publisher or rights context: {publisher}.] [Availability: {availability}.] [Themes and genres: {genres}.] Description: {overview[:520]}","metadata_sha256":"8acbacbf691362a08bc34412a4f12919f4b571b1984c006f74cda6e1a12d4b28","breakdown":{"podcast":18,"game":99,"short":13,"live":7,"film":133333,"series":66667},"vectors_file":"SUMMON_field_vectors.f32","norms_file":"SUMMON_field_norms.f32","metadata_files":["SUMMON_field_metadata_01.json","SUMMON_field_metadata_02.json","SUMMON_field_metadata_03.json","SUMMON_field_metadata_04.json","SUMMON_field_metadata_05.json"]}